{
  "Ashford International": "Ashford Intl",
  "Aylesbury Vale Parkway": "Aylesbury Vale P'way",
  "Bradford Forster Square": "Bradford Forster Sq",
  "Bristol Temple Meads": "Bristol Temple Mds",
  "Birmingham International": "Birmingham Intl",
  "Birmingham Moor Street": "Birmingham Moor St",
  "Birmingham New Street": "Birmingham New St",
  "Birmingham Snow Hill": "Birmingham Snow ...",
  "Glasgow Queen Street": "Glasgow Queen St",
  "Liverpool Lime Street": "Liverpool Lime St",
  "London Cannon Street": "London Cannon St",
  "London Charing Cross": "London Charing X",
  "London Fenchurch Street": "London Fenchurch St",
  "London Liverpool Street": "London Liverpool St",
  "London St Pancras (Intl)": "London St Pancras",
  "Manchester Oxford Road": "Manchester Oxf'd Rd",
  "Milton Keynes Central": "Milton Keynes Ctl",
  "Newport (South Wales)": "Newport (Wales)",
  "Portsmouth & Southsea": "Portsmouth & S'sea",
  "Queens Park (Glasgow)": "Queens Park (G'gow)",
  "Severn Tunnel Junction": "Severn Tunnel Jctn",
  "Stourbridge Junction": "Stourbridge Jctn",
  "West Hampstead Thameslink": "West Hampstead TL",
  "Windsor & Eton Central": "Windsor & Eton Ctl",
  "Worcester Foregate Street": "Worcester F'gate St",
  "Worcester Shrub Hill": "Worcester Shrub ...",
}
